{"organe": {"@xmlns:xsi": "http://www.w3.org/2001/XMLSchema-instance", "uid": "PO322774", "codeType": "ORGEXTPARL", "libelle": "Conseil national du littoral", "libelleEdition": "du conseil national du littoral", "libelleAbrege": "Littoral", "libelleAbrev": "219", "viMoDe": {"dateDebut": "2005-11-18", "dateAgrement": null, "dateFin": "2010-07-12"}, "organeParent": null, "chambre": null, "regime": "5\u00e8me R\u00e9publique", "legislature": null, "regimeJuridique": "Art. 2 du D n\u00b02005-1426 du 18.11.2005", "siteInternet": null, "nombreReunionsAnnuelles": null}}