{"organe": {"@xmlns:xsi": "http://www.w3.org/2001/XMLSchema-instance", "uid": "PO383109", "codeType": "ORGEXTPARL", "libelle": "Conseil d'administration de l'Agence nationale pour la coh\u00e9sion sociale et l'\u00e9galit\u00e9 des chances", "libelleEdition": "du conseil d'administration de l'Agence nationale pour la coh\u00e9sion sociale et l'\u00e9galit\u00e9 des chances", "libelleAbrege": "Coh\u00e9sion sociale et \u00e9galit\u00e9 des chance", "libelleAbrev": "232", "viMoDe": {"dateDebut": "2006-07-28", "dateAgrement": null, "dateFin": "2017-01-01"}, "organeParent": null, "chambre": null, "regime": "5\u00e8me R\u00e9publique", "legislature": null, "regimeJuridique": "Article R. 121-14 du code de l\u2019action sociale et des familles", "siteInternet": null, "nombreReunionsAnnuelles": null}}