{"organe": {"@xmlns:xsi": "http://www.w3.org/2001/XMLSchema-instance", "uid": "PO60298", "codeType": "ORGEXTPARL", "libelle": "Conseil sup\u00e9rieur du service public ferroviaire", "libelleEdition": "du conseil sup\u00e9rieur du service public ferroviaire", "libelleAbrege": "Ferroviaire (Service public )", "libelleAbrev": "159", "viMoDe": {"dateDebut": "1999-03-19", "dateAgrement": null, "dateFin": "2011-01-24"}, "organeParent": null, "chambre": null, "regime": "5\u00e8me R\u00e9publique", "legislature": null, "regimeJuridique": "D\u00e9cret 99-221 du 19 mars 1999", "siteInternet": null, "nombreReunionsAnnuelles": null}}