{"organe": {"@xmlns:xsi": "http://www.w3.org/2001/XMLSchema-instance", "uid": "PO701979", "codeType": "COMSPSENAT", "libelle": "Commission sp\u00e9ciale D\u00e9limitation des r\u00e9gions, \u00e9lections r\u00e9gionales et d\u00e9partementales et calendrier \u00e9lectoral", "libelleEdition": null, "libelleAbrege": "Commission sp\u00e9ciale D\u00e9limitation des r\u00e9gions, \u00e9lections r\u00e9gionales et d\u00e9partemen", "libelleAbrev": "REGIO", "viMoDe": {"dateDebut": "2014-06-18", "dateAgrement": null, "dateFin": "2015-01-17"}, "organeParent": null}}