{"mandat": {"uid": "PM393712", "acteurRef": "PA267289", "legislature": "13", "typeOrgane": "OFFPAR", "dateDebut": "2007-07-25", "datePublication": "2007-07-25", "dateFin": "2009-06-15", "preseance": "16", "nominPrincipale": "1", "infosQualite": {"codeQualite": "Membre de droit (Rapporteur du projet de loi de financement de la s\u00e9c. sociale)", "libQualite": "Membre de droit (Rapporteur du projet de loi de financement de la s\u00e9curit\u00e9 sociale)", "libQualiteSex": "Membre de droit (Rapporteur du projet de loi de financement de la s\u00e9curit\u00e9 sociale)"}, "organes": {"organeRef": "PO288529"}, "suppleants": null}}