{"mandat": {"@xmlns:xsi": "http://www.w3.org/2001/XMLSchema-instance", "uid": "PM429585", "acteurRef": "PA427304", "legislature": "13", "typeOrgane": "ASSEMBLEE", "dateDebut": "2009-10-18", "datePublication": "2009-10-19", "dateFin": "2012-06-16", "preseance": "50", "nominPrincipale": "1", "infosQualite": {"codeQualite": "membre", "libQualite": "membre", "libQualiteSex": "membre"}, "organes": {"organeRef": "PO384266"}, "suppleants": null, "chambre": null, "election": {"lieu": {"region": "Ile-de-France", "regionType": "M\u00e9tropolitain", "departement": "Yvelines", "numDepartement": "78", "numCirco": "12"}, "causeMandat": "remplacement d'un d\u00e9put\u00e9 nomm\u00e9 au Gouvernement", "refCirconscription": "PO384715"}, "mandature": {"datePriseFonction": "2011-07-30", "causeFin": "Reprise de l'exercice du mandat d'un ancien membre du Gouvernement", "premiereElection": "0", "placeHemicycle": null, "mandatRemplaceRef": "PM386404"}, "collaborateurs": null}}