{"mandat": {"@xmlns:xsi": "http://www.w3.org/2001/XMLSchema-instance", "uid": "PM688045", "acteurRef": "PA610968", "legislature": "14", "typeOrgane": "MISINFOPRE", "dateDebut": "2013-01-16", "datePublication": "2013-01-17", "dateFin": "2013-07-02", "preseance": "8", "nominPrincipale": "1", "infosQualite": {"codeQualite": "Secr\u00e9taire", "libQualite": "Secr\u00e9taire", "libQualiteSex": "Secr\u00e9taire"}, "organes": {"organeRef": "PO684894"}, "libelle": null, "missionSuivanteRef": null, "missionPrecedenteRef": null}}