{"mandat": {"@xmlns:xsi": "http://www.w3.org/2001/XMLSchema-instance", "uid": "PM704753", "acteurRef": "PA1226", "legislature": "14", "typeOrgane": "MINISTERE", "dateDebut": "2014-11-25", "datePublication": "2014-11-26", "dateFin": "2015-05-24", "preseance": "1", "nominPrincipale": "1", "infosQualite": {"codeQualite": "en mission", "libQualite": "en mission", "libQualiteSex": "en mission"}, "organes": {"organeRef": "PO702908"}, "libelle": "L'avenir des trains d'\u00e9quilibre du territoire", "missionSuivanteRef": null, "missionPrecedenteRef": null}}