{"mandat": {"@xmlns:xsi": "http://www.w3.org/2001/XMLSchema-instance", "uid": "PM760913", "acteurRef": "PA720738", "legislature": "15", "typeOrgane": "MINISTERE", "dateDebut": "2018-12-10", "datePublication": "2018-12-11", "dateFin": null, "preseance": "1", "nominPrincipale": "1", "infosQualite": {"codeQualite": "en mission", "libQualite": "en mission", "libQualiteSex": "en mission"}, "organes": {"organeRef": "PO730302"}, "libelle": "La participation des personnes handicap\u00e9es \u00e0 la d\u00e9cision publique et au conseil national consultatif des personnes handicap\u00e9es", "missionSuivanteRef": null, "missionPrecedenteRef": null}}