{"acteur": {"@xmlns:xsi": "http://www.w3.org/2001/XMLSchema-instance", "uid": {"@xsi:type": "IdActeur_type", "#text": "PA335017"}, "etatCivil": {"ident": {"civ": "M.", "prenom": "Christophe", "nom": "Sirugue", "alpha": "Sirugue", "trigramme": null}, "infoNaissance": {"dateNais": "1966-08-14", "villeNais": "Autun", "depNais": "Sa\u00f4ne-et-Loire", "paysNais": "France"}, "dateDeces": null}, "profession": {"libelleCourant": "Cadre sup\u00e9rieur du secteur priv\u00e9", "socProcINSEE": {"catSocPro": "Cadres d'entreprise", "famSocPro": "Cadres et professions intellectuelles sup\u00e9rieures"}}, "uri_hatvp": null, "adresses": {"adresse": [{"@xsi:type": "AdressePostale_Type", "uid": "AD386958", "type": "0", "typeLibelle": "Adresse officielle", "poids": "1", "adresseDeRattachement": null, "intitule": "Assembl\u00e9e nationale,", "numeroRue": "126", "nomRue": "Rue de l'Universit\u00e9,", "complementAdresse": null, "codePostal": "75355", "ville": "Paris 07 SP"}, {"@xsi:type": "AdresseMail_Type", "uid": "AD392060", "type": "15", "typeLibelle": "M\u00e8l", "poids": null, "adresseDeRattachement": null, "valElec": "csirugue@assemblee-nationale.fr"}, {"@xsi:type": "AdressePostale_Type", "uid": "AD400056", "type": "2", "typeLibelle": "Adresse publi\u00e9e de circonscription", "poids": "22", "adresseDeRattachement": null, "intitule": "Permanence", "numeroRue": "22", "nomRue": "Rue de la Banque", "complementAdresse": null, "codePostal": "71100", "ville": "Chalon-sur-Sa\u00f4ne"}, {"@xsi:type": "AdresseTelephonique_Type", "uid": "AD400057", "type": "11", "typeLibelle": "T\u00e9l\u00e9phone", "poids": "22", "adresseDeRattachement": "AD400056", "valElec": "03 85 90 04 30"}, {"@xsi:type": "AdresseTelephonique_Type", "uid": "AD400058", "type": "12", "typeLibelle": "T\u00e9l\u00e9copie", "poids": "22", "adresseDeRattachement": "AD400056", "valElec": "03 85 93 18 49"}, {"@xsi:type": "AdresseSiteWeb_Type", "uid": "AD700639", "type": "22", "typeLibelle": "Site internet", "poids": null, "adresseDeRattachement": null, "valElec": "www.christophesirugue.fr"}]}}}