{"acteur": {"@xmlns:xsi": "http://www.w3.org/2001/XMLSchema-instance", "uid": {"@xsi:type": "IdActeur_type", "#text": "PA332747"}, "etatCivil": {"ident": {"civ": "M.", "prenom": "Fran\u00e7ois", "nom": "de Rugy", "alpha": "Rugy (de)", "trigramme": null}, "infoNaissance": {"dateNais": "1973-12-06", "villeNais": "Nantes", "depNais": "Loire-Atlantique", "paysNais": "France"}, "dateDeces": null}, "profession": {"libelleCourant": "Assistant parlementaire", "socProcINSEE": {"catSocPro": "Cadres de la fonction publique, professions intellectuelles et  artistiques", "famSocPro": "Cadres et professions intellectuelles sup\u00e9rieures"}}, "uri_hatvp": null, "adresses": {"adresse": [{"@xsi:type": "AdressePostale_Type", "uid": "AD386781", "type": "0", "typeLibelle": "Adresse officielle", "poids": "1", "adresseDeRattachement": null, "intitule": "Assembl\u00e9e nationale,", "numeroRue": "126", "nomRue": "Rue de l'Universit\u00e9,", "complementAdresse": null, "codePostal": "75355", "ville": "Paris 07 SP"}, {"@xsi:type": "AdresseMail_Type", "uid": "AD388375", "type": "15", "typeLibelle": "M\u00e8l", "poids": null, "adresseDeRattachement": null, "valElec": "accueil@francoisderugy.net"}, {"@xsi:type": "AdresseMail_Type", "uid": "AD392088", "type": "15", "typeLibelle": "M\u00e8l", "poids": null, "adresseDeRattachement": null, "valElec": "francois.derugy@assemblee-nationale.fr"}, {"@xsi:type": "AdressePostale_Type", "uid": "AD413959", "type": "2", "typeLibelle": "Adresse publi\u00e9e de circonscription", "poids": "22", "adresseDeRattachement": null, "intitule": null, "numeroRue": "14", "nomRue": "Quai de Versailles", "complementAdresse": null, "codePostal": "44000", "ville": "Nantes"}, {"@xsi:type": "AdresseSiteWeb_Type", "uid": "AD716938", "type": "22", "typeLibelle": "Site internet", "poids": null, "adresseDeRattachement": null, "valElec": "www.francoisderugy.fr"}, {"@xsi:type": "AdresseSiteWeb_Type", "uid": "AD725956", "type": "25", "typeLibelle": "Facebook", "poids": null, "adresseDeRattachement": null, "valElec": "francoisderugy"}, {"@xsi:type": "AdresseSiteWeb_Type", "uid": "AD726488", "type": "24", "typeLibelle": "Twitter", "poids": null, "adresseDeRattachement": null, "valElec": "@Fderugy"}]}}}