{"acteur": {"@xmlns:xsi": "http://www.w3.org/2001/XMLSchema-instance", "uid": {"@xsi:type": "IdActeur_type", "#text": "PA522"}, "etatCivil": {"ident": {"civ": "M.", "prenom": "Jean-Marie", "nom": "Binetruy", "alpha": "Binetruy", "trigramme": null}, "infoNaissance": {"dateNais": "1946-07-17", "villeNais": "Villers-le-Lac", "depNais": "Doubs", "paysNais": "France"}, "dateDeces": null}, "profession": {"libelleCourant": "Enseignant", "socProcINSEE": {"catSocPro": "Professions interm\u00e9diaires de l'enseignement, de la sant\u00e9, de la fonction publique et assimil\u00e9s", "famSocPro": "Professions Interm\u00e9diaires"}}, "uri_hatvp": null, "adresses": {"adresse": [{"@xsi:type": "AdressePostale_Type", "uid": "AD13113", "type": "2", "typeLibelle": "Adresse publi\u00e9e de circonscription", "poids": "21", "adresseDeRattachement": null, "intitule": "H\u00f4tel de Ville,", "numeroRue": null, "nomRue": null, "complementAdresse": "BP 53095,", "codePostal": "25503", "ville": "Morteau"}, {"@xsi:type": "AdresseTelephonique_Type", "uid": "AD13120", "type": "11", "typeLibelle": "T\u00e9l\u00e9phone", "poids": "21", "adresseDeRattachement": "AD13113", "valElec": "03 81 68 56 56"}, {"@xsi:type": "AdresseTelephonique_Type", "uid": "AD13122", "type": "12", "typeLibelle": "T\u00e9l\u00e9copie", "poids": "21", "adresseDeRattachement": "AD13113", "valElec": "03 81 67 25 09"}, {"@xsi:type": "AdressePostale_Type", "uid": "AD274957", "type": "2", "typeLibelle": "Adresse publi\u00e9e de circonscription", "poids": "22", "adresseDeRattachement": null, "intitule": "Permanence,", "numeroRue": "5", "nomRue": "Rue du Parc", "complementAdresse": null, "codePostal": "25300", "ville": "Pontarlier"}, {"@xsi:type": "AdresseTelephonique_Type", "uid": "AD274961", "type": "11", "typeLibelle": "T\u00e9l\u00e9phone", "poids": "22", "adresseDeRattachement": "AD274957", "valElec": "03 81 38 88 80"}, {"@xsi:type": "AdresseTelephonique_Type", "uid": "AD274962", "type": "12", "typeLibelle": "T\u00e9l\u00e9copie", "poids": "22", "adresseDeRattachement": "AD274957", "valElec": "03 81 38 86 27"}, {"@xsi:type": "AdresseMail_Type", "uid": "AD275088", "type": "15", "typeLibelle": "M\u00e8l", "poids": null, "adresseDeRattachement": null, "valElec": "jean-marie.binetruy@wanadoo.fr"}, {"@xsi:type": "AdresseSiteWeb_Type", "uid": "AD313807", "type": "22", "typeLibelle": "Site internet", "poids": null, "adresseDeRattachement": null, "valElec": "jeanmariebinetruy.blogspirit.com/"}, {"@xsi:type": "AdressePostale_Type", "uid": "AD386684", "type": "0", "typeLibelle": "Adresse officielle", "poids": "1", "adresseDeRattachement": null, "intitule": "Assembl\u00e9e nationale,", "numeroRue": "126", "nomRue": "Rue de l'Universit\u00e9,", "complementAdresse": null, "codePostal": "75355", "ville": "Paris 07 SP"}, {"@xsi:type": "AdresseMail_Type", "uid": "AD391596", "type": "15", "typeLibelle": "M\u00e8l", "poids": null, "adresseDeRattachement": null, "valElec": "jmbinetruy@assemblee-nationale.fr"}]}}}