{"acteur": {"@xmlns:xsi": "http://www.w3.org/2001/XMLSchema-instance", "uid": {"@xsi:type": "IdActeur_type", "#text": "PA642684"}, "etatCivil": {"ident": {"civ": "M.", "prenom": "Jean-Pierre", "nom": "Maggi", "alpha": "Maggi", "trigramme": null}, "infoNaissance": {"dateNais": "1944-04-27", "villeNais": "Marseille", "depNais": "Bouches-du-Rh\u00f4ne", "paysNais": "France"}, "dateDeces": null}, "profession": {"libelleCourant": null, "socProcINSEE": {"catSocPro": null, "famSocPro": null}}, "uri_hatvp": null, "adresses": {"adresse": [{"@xsi:type": "AdressePostale_Type", "uid": "AD663908", "type": "0", "typeLibelle": "Adresse officielle", "poids": "1", "adresseDeRattachement": null, "intitule": "Assembl\u00e9e nationale", "numeroRue": "126", "nomRue": "Rue de l'Universit\u00e9", "complementAdresse": null, "codePostal": "75355", "ville": "Paris 07 SP"}, {"@xsi:type": "AdressePostale_Type", "uid": "AD672191", "type": "2", "typeLibelle": "Adresse publi\u00e9e de circonscription", "poids": "22", "adresseDeRattachement": null, "intitule": "Permanence parlementaire", "numeroRue": "17", "nomRue": "Rue Blanchard", "complementAdresse": null, "codePostal": "13300", "ville": "Salon-de-Provence"}, {"@xsi:type": "AdresseTelephonique_Type", "uid": "AD672192", "type": "11", "typeLibelle": "T\u00e9l\u00e9phone", "poids": "22", "adresseDeRattachement": "AD672191", "valElec": "09 67 27 30 97"}, {"@xsi:type": "AdresseMail_Type", "uid": "AD672205", "type": "15", "typeLibelle": "M\u00e8l", "poids": null, "adresseDeRattachement": null, "valElec": "jpmaggi@assemblee-nationale.fr"}, {"@xsi:type": "AdresseTelephonique_Type", "uid": "AD677705", "type": "11", "typeLibelle": "T\u00e9l\u00e9phone", "poids": "1", "adresseDeRattachement": "AD663908", "valElec": "01 40 63 48 16"}]}}}