{"acteur": {"@xmlns:xsi": "http://www.w3.org/2001/XMLSchema-instance", "uid": {"@xsi:type": "IdActeur_type", "#text": "PA642695"}, "etatCivil": {"ident": {"civ": "M.", "prenom": "\u00c9ric", "nom": "Bothorel", "alpha": "Bothorel", "trigramme": "EBO"}, "infoNaissance": {"dateNais": "1966-10-20", "villeNais": "Paimpol", "depNais": "C\u00f4tes-d'Armor", "paysNais": "France"}, "dateDeces": null}, "profession": {"libelleCourant": "Cadre sup\u00e9rieur (secteur priv\u00e9)", "socProcINSEE": {"catSocPro": "Cadres d'entreprise", "famSocPro": "Cadres et professions intellectuelles sup\u00e9rieures"}}, "uri_hatvp": "https://www.hatvp.fr/pages_nominatives/bothorel-eric", "adresses": {"adresse": [{"@xsi:type": "AdressePostale_Type", "uid": "AD717132", "type": "0", "typeLibelle": "Adresse officielle", "poids": "1", "adresseDeRattachement": null, "intitule": "Assembl\u00e9e nationale", "numeroRue": "126", "nomRue": "Rue de l'Universit\u00e9,", "complementAdresse": null, "codePostal": "75355", "ville": "Paris 07 SP"}, {"@xsi:type": "AdresseMail_Type", "uid": "AD727948", "type": "15", "typeLibelle": "M\u00e8l", "poids": null, "adresseDeRattachement": null, "valElec": "eric.bothorel@assemblee-nationale.fr"}, {"@xsi:type": "AdressePostale_Type", "uid": "AD728460", "type": "2", "typeLibelle": "Adresse publi\u00e9e de circonscription", "poids": "22", "adresseDeRattachement": null, "intitule": null, "numeroRue": "32", "nomRue": "Place du Marchallac'h", "complementAdresse": null, "codePostal": "22300", "ville": "Lannion"}, {"@xsi:type": "AdresseSiteWeb_Type", "uid": "AD729154", "type": "24", "typeLibelle": "Twitter", "poids": null, "adresseDeRattachement": null, "valElec": "@ebothorel"}, {"@xsi:type": "AdresseSiteWeb_Type", "uid": "AD747532", "type": "25", "typeLibelle": "Facebook", "poids": null, "adresseDeRattachement": null, "valElec": "Eric-Bothorel-D\u00e9put\u00e9-circo2205"}, {"@xsi:type": "AdresseSiteWeb_Type", "uid": "AD747534", "type": "22", "typeLibelle": "Site internet", "poids": null, "adresseDeRattachement": null, "valElec": "ericbothorel.fr"}, {"@xsi:type": "AdresseTelephonique_Type", "uid": "AD753822", "type": "11", "typeLibelle": "T\u00e9l\u00e9phone", "poids": "22", "adresseDeRattachement": "AD728460", "valElec": "02 96 37 03 23"}, {"@xsi:type": "AdresseMail_Type", "uid": "AD753824", "type": "15", "typeLibelle": "M\u00e8l", "poids": "22", "adresseDeRattachement": "AD728460", "valElec": "contact@ericbothorel.bzh"}]}}}