{"acteur": {"@xmlns:xsi": "http://www.w3.org/2001/XMLSchema-instance", "uid": {"@xsi:type": "IdActeur_type", "#text": "PA718784"}, "etatCivil": {"ident": {"civ": "M.", "prenom": "\u00c9ric", "nom": "Pauget", "alpha": "Pauget", "trigramme": "EPA"}, "infoNaissance": {"dateNais": "1970-08-18", "villeNais": "Antibes", "depNais": "Alpes-Maritimes", "paysNais": "France"}, "dateDeces": null}, "profession": {"libelleCourant": "Autre cadre (secteur priv\u00e9)", "socProcINSEE": {"catSocPro": "Cadres d'entreprise", "famSocPro": "Cadres et professions intellectuelles sup\u00e9rieures"}}, "uri_hatvp": "https://www.hatvp.fr/pages_nominatives/pauget-eric-6497", "adresses": {"adresse": [{"@xsi:type": "AdressePostale_Type", "uid": "AD718786", "type": "0", "typeLibelle": "Adresse officielle", "poids": "1", "adresseDeRattachement": null, "intitule": "Assembl\u00e9e nationale,", "numeroRue": "126", "nomRue": "Rue de l'Universit\u00e9,", "complementAdresse": null, "codePostal": "75355", "ville": "Paris 07 SP"}, {"@xsi:type": "AdresseSiteWeb_Type", "uid": "AD725766", "type": "24", "typeLibelle": "Twitter", "poids": null, "adresseDeRattachement": null, "valElec": "@EricPAUGET1"}, {"@xsi:type": "AdresseMail_Type", "uid": "AD725854", "type": "15", "typeLibelle": "M\u00e8l", "poids": null, "adresseDeRattachement": null, "valElec": "e.pauget@orange.fr"}, {"@xsi:type": "AdressePostale_Type", "uid": "AD725952", "type": "2", "typeLibelle": "Adresse publi\u00e9e de circonscription", "poids": "22", "adresseDeRattachement": null, "intitule": null, "numeroRue": "6", "nomRue": "Rue Sadi Carnot", "complementAdresse": null, "codePostal": "06600", "ville": "Antibes"}, {"@xsi:type": "AdresseTelephonique_Type", "uid": "AD725954", "type": "11", "typeLibelle": "T\u00e9l\u00e9phone", "poids": "22", "adresseDeRattachement": "AD725952", "valElec": "04 93 67 03 30"}, {"@xsi:type": "AdresseMail_Type", "uid": "AD727974", "type": "15", "typeLibelle": "M\u00e8l", "poids": null, "adresseDeRattachement": null, "valElec": "eric.pauget@assemblee-nationale.fr"}, {"@xsi:type": "AdresseSiteWeb_Type", "uid": "AD751289", "type": "22", "typeLibelle": "Site internet", "poids": null, "adresseDeRattachement": null, "valElec": "www.ericpauget.fr"}, {"@xsi:type": "AdresseSiteWeb_Type", "uid": "AD751291", "type": "25", "typeLibelle": "Facebook", "poids": null, "adresseDeRattachement": null, "valElec": "PaugetDepute"}]}}}