{"acteur": {"@xmlns:xsi": "http://www.w3.org/2001/XMLSchema-instance", "uid": {"@xsi:type": "IdActeur_type", "#text": "PA718756"}, "etatCivil": {"ident": {"civ": "Mme", "prenom": "Aude", "nom": "Bono-Vandorme", "alpha": "BonoVandorme", "trigramme": "ABO"}, "infoNaissance": {"dateNais": "1962-08-03", "villeNais": "Soissons", "depNais": "Aisne", "paysNais": "France"}, "dateDeces": null}, "profession": {"libelleCourant": "Profession rattach\u00e9e \u00e0 l'enseignement", "socProcINSEE": {"catSocPro": "Cadres de la fonction publique, professions intellectuelles et  artistiques", "famSocPro": "Cadres et professions intellectuelles sup\u00e9rieures"}}, "uri_hatvp": "https://www.hatvp.fr/pages_nominatives/bono-vandorme-aude", "adresses": {"adresse": [{"@xsi:type": "AdressePostale_Type", "uid": "AD718758", "type": "0", "typeLibelle": "Adresse officielle", "poids": "1", "adresseDeRattachement": null, "intitule": "Assembl\u00e9e nationale,", "numeroRue": "126", "nomRue": "Rue de l'Universit\u00e9,", "complementAdresse": null, "codePostal": "75355", "ville": "Paris 07 SP"}, {"@xsi:type": "AdressePostale_Type", "uid": "AD726696", "type": "2", "typeLibelle": "Adresse publi\u00e9e de circonscription", "poids": "22", "adresseDeRattachement": null, "intitule": null, "numeroRue": "191", "nomRue": "Boulevard Pierre Brossolette", "complementAdresse": null, "codePostal": "02000", "ville": "Laon"}, {"@xsi:type": "AdresseMail_Type", "uid": "AD727971", "type": "15", "typeLibelle": "M\u00e8l", "poids": null, "adresseDeRattachement": null, "valElec": "aude.bono-vandorme@assemblee-nationale.fr"}, {"@xsi:type": "AdresseSiteWeb_Type", "uid": "AD759115", "type": "22", "typeLibelle": "Site internet", "poids": null, "adresseDeRattachement": null, "valElec": "aude-bono-vandorme.fr/"}, {"@xsi:type": "AdresseSiteWeb_Type", "uid": "AD759118", "type": "25", "typeLibelle": "Facebook", "poids": null, "adresseDeRattachement": null, "valElec": "ABonoVandorme"}]}}}